nlpp/__init__.py
nlpp/__main__.py
nlpp/utils.py
nlpp/ana/__init__.py
nlpp/ana/_ana.py
nlpp/ana/keyword_search.py
nlpp/model/__init__.py
nlpp/model/_document.py
nlpp/model/corpus.py
nlpp/model/corpus_funcs.py
nlpp/model/document.py
nlpp/parser/__init__.py
nlpp/parser/_pdfparser.py
nlpp/parser/add.py
nlpp/parser/parser.py
nlpp/token/__init__.py
nlpp/token/tokenseq_funcs.py
tests/__init__.py
tests/test_corpus.py
fsm_nlp-0.0.21.dist-info/METADATA
fsm_nlp-0.0.21.dist-info/WHEEL
fsm_nlp-0.0.21.dist-info/top_level.txt
fsm_nlp-0.0.21.dist-info/RECORD
